pyodbc.cpython-38-darwin.so
pyodbc.pyi
pyodbc-5.1.0.dist-info/LICENSE.txt
pyodbc-5.1.0.dist-info/METADATA
pyodbc-5.1.0.dist-info/WHEEL
pyodbc-5.1.0.dist-info/top_level.txt
pyodbc-5.1.0.dist-info/RECORD
